shiba2sashimi/__init__.py
shiba2sashimi/bams.py
shiba2sashimi/junc.py
shiba2sashimi/main.py
shiba2sashimi/plots.py
shiba2sashimi/tables.py
shiba2sashimi/utils.py
shiba2sashimi-0.1.7.dist-info/licenses/LICENSE
shiba2sashimi-0.1.7.dist-info/METADATA
shiba2sashimi-0.1.7.dist-info/WHEEL
shiba2sashimi-0.1.7.dist-info/entry_points.txt
shiba2sashimi-0.1.7.dist-info/top_level.txt
shiba2sashimi-0.1.7.dist-info/RECORD
