Metadata-Version: 2.4
Name: shiba2sashimi
Version: 0.1.7
Summary: A utility for creating sashimi plot from Shiba output
Author-email: Naoto Kubota <the.owner.of.the.dream123@gmail.com>
License: MIT
Project-URL: Homepage, https://github.com/Sika-Zheng-Lab/shiba2sashimi
Requires-Python: >=3.9
License-File: LICENSE
Requires-Dist: numpy<2.0.0,>=1.18.0
Requires-Dist: matplotlib>=3.1.0
Requires-Dist: pysam>=0.22.0
Dynamic: license-file
